inputs.py
inputs-0.4.dist-info/METADATA
inputs-0.4.dist-info/RECORD
inputs-0.4.dist-info/WHEEL
inputs-0.4.dist-info/top_level.txt
