Metadata-Version: 2.1
Name: inputs
Version: 0.4
Summary: Cross-platform Python support for keyboards, mice and gamepads.
Home-page: https://github.com/zeth/inputs
Author: Zeth
Author-email: theology@gmail.com
License: BSD
Platform: UNKNOWN
Classifier: Programming Language :: Python :: 2.7
Classifier: Programming Language :: Python :: 3
Classifier: Intended Audience :: Developers
Classifier: License :: OSI Approved :: BSD License
Classifier: Topic :: Software Development :: Libraries
Classifier: Topic :: Utilities
Classifier: Topic :: System :: Hardware :: Hardware Drivers
Classifier: Topic :: Software Development :: Embedded Systems
Classifier: Operating System :: POSIX :: Linux
Classifier: Operating System :: Microsoft :: Windows
Classifier: Operating System :: MacOS :: MacOS X
